aaaamcpuser/__init__.py
aaaamcpuser/__main__.py
aaaamcpuser/main.py
aaaamcpuser-0.1.4.dist-info/METADATA
aaaamcpuser-0.1.4.dist-info/WHEEL
aaaamcpuser-0.1.4.dist-info/entry_points.txt
aaaamcpuser-0.1.4.dist-info/top_level.txt
aaaamcpuser-0.1.4.dist-info/RECORD
